MANIFEST.in
README.md
setup.py
aspose_barcode_for_python_via_java.egg-info/PKG-INFO
aspose_barcode_for_python_via_java.egg-info/SOURCES.txt
aspose_barcode_for_python_via_java.egg-info/dependency_links.txt
aspose_barcode_for_python_via_java.egg-info/requires.txt
aspose_barcode_for_python_via_java.egg-info/top_level.txt
asposebarcode/Assist.py
asposebarcode/ComplexBarcode.py
asposebarcode/Generation.py
asposebarcode/Recognition.py
asposebarcode/__init__.py
asposebarcode/jlib/aspose-barcode-python-26.1.jar
license/End+User+License+Agreement.html
license/ThirdPartyLicenses.Aspose.BarCode.Java.pdf