Metadata-Version: 2.1
Name: aspose-barcode-for-python-via-java
Version: 26.1.0
Summary: Barcode generation and recognition component. It allows developers to quickly and easily add barcode creation and scanning functionality to their Python applications.
Home-page: UNKNOWN
Author: Aspose
Author-email: aleksander.grinin@aspose.com
License: UNKNOWN
Keywords: aspose,barcode,java
Platform: UNKNOWN
Classifier: Programming Language :: Python :: 3.6
Classifier: License :: Other/Proprietary License
Requires-Python: >=3.6
